rotating_logger/__init__.py
rotating_logger/native_logger.py
rotate_logger-1.1.0.dist-info/METADATA
rotate_logger-1.1.0.dist-info/WHEEL
rotate_logger-1.1.0.dist-info/top_level.txt
rotate_logger-1.1.0.dist-info/RECORD
