Metadata-Version: 2.1
Name: rotate-logger
Version: 1.1.0
Summary: Package for rotating logger
Home-page: https://github.com/rezandry/rotating-logger-python
Author: Reza Andriyunanto
Author-email: andriyunantoreza@gmail.com
License: UNKNOWN
Platform: UNKNOWN
Classifier: Programming Language :: Python :: 3
Classifier: License :: OSI Approved :: MIT License
Classifier: Operating System :: OS Independent
